chemhelp/__init__.py
chemhelp/help.py
chemhelp-0.0.4.dist-info/METADATA
chemhelp-0.0.4.dist-info/WHEEL
chemhelp-0.0.4.dist-info/licenses/LICENSE
chemhelp-0.0.4.dist-info/RECORD
